raaju1/__init__.py
raaju1/main.py
raaju1-1.3.4.dist-info/METADATA
raaju1-1.3.4.dist-info/WHEEL
raaju1-1.3.4.dist-info/entry_points.txt
raaju1-1.3.4.dist-info/top_level.txt
raaju1-1.3.4.dist-info/RECORD
