Metadata-Version: 2.4
Name: raaju1
Version: 1.3.4
Author: Raaj
Dynamic: author
Dynamic: description
Dynamic: description-content-type
